Workbook

Sheet DASHBOARD
B2: FOOTBALL SCOUTING | PLAYER COMPARISON DASHBOARD
B4: PLAYER 1 | F4: VS | H4: PLAYER 2
B5: Bruno Fernandes | H5: Bernardo Silva
B6: Club | C6: =IFERROR(XLOOKUP($B$5,DATA!$A:$A,DATA!$C:$C,"--"),"--") | I6: =IFERROR(XLOOKUP($H$5,DATA!$A:$A,DATA!$C:$C,"--"),"--")
B7: Position | C7: =IFERROR(XLOOKUP($B$5,DATA!$A:$A,DATA!$D:$D,"--"),"--") | I7: =IFERROR(XLOOKUP($H$5,DATA!$A:$A,DATA!$D:$D,"--"),"--")
B8: Nat. | C8: =IFERROR(XLOOKUP($B$5,DATA!$A:$A,DATA!$E:$E,"--"),"--") | I8: =IFERROR(XLOOKUP($H$5,DATA!$A:$A,DATA!$E:$E,"--"),"--")
B9: Age | C9: =IFERROR(XLOOKUP($B$5,DATA!$A:$A,DATA!$B:$B,"--"),"--") | I9: =IFERROR(XLOOKUP($H$5,DATA!$A:$A,DATA!$B:$B,"--"),"--")
B10: Rating | C10: =IFERROR(ROUND(XLOOKUP($B$5,DATA!$A:$A,DATA!$F:$F,0),1),"--") | I10: =IFERROR(ROUND(XLOOKUP($H$5,DATA!$A:$A,DATA!$F:$F,0),1),"--")
B12: PERCENTILE SCORES ( 0 = lowest / 100 = highest in database )
B14: Scoring | D14: Creating | F14: Defending | H14: Possession | J14: Dribbling
B15: =IFERROR(ROUND(XLOOKUP($B$5,DATA!$A:$A,DATA!$V:$V,0),1),"--") | D15: =IFERROR(ROUND(XLOOKUP($B$5,DATA!$A:$A,DATA!$Y:$Y,0),1),"--") | F15: =IFERROR(ROUND(XLOOKUP($B$5,DATA!$A:$A,DATA!$Z:$Z,0),1),"--") | H15: =IFERROR(ROUND(XLOOKUP($B$5,DATA!$A:$A,DATA!$AB:$AB,0),1),"--") | J15: =IFERROR(ROUND(XLOOKUP($B$5,DATA!$A:$A,DATA!$AC:$AC,0),1),"--")
B16: =IFERROR(ROUND(XLOOKUP($H$5,DATA!$A:$A,DATA!$V:$V,0),1),"--") | D16: =IFERROR(ROUND(XLOOKUP($H$5,DATA!$A:$A,DATA!$Y:$Y,0),1),"--") | F16: =IFERROR(ROUND(XLOOKUP($H$5,DATA!$A:$A,DATA!$Z:$Z,0),1),"--") | H16: =IFERROR(ROUND(XLOOKUP($H$5,DATA!$A:$A,DATA!$AB:$AB,0),1),"--") | J16: =IFERROR(ROUND(XLOOKUP($H$5,DATA!$A:$A,DATA!$AC:$AC,0),1),"--")
B17: =IFERROR(ROUND(XLOOKUP($B$5,DATA!$A:$A,DATA!$V:$V,0)-XLOOKUP($H$5,DATA!$A:$A,DATA!$V:$V,0),1),"--") | D17: =IFERROR(ROUND(XLOOKUP($B$5,DATA!$A:$A,DATA!$Y:$Y,0)-XLOOKUP($H$5,DATA!$A:$A,DATA!$Y:$Y,0),1),"--") | F17: =IFERROR(ROUND(XLOOKUP($B$5,DATA!$A:$A,DATA!$Z:$Z,0)-XLOOKUP($H$5,DATA!$A:$A,DATA!$Z:$Z,0),1),"--") | H17: =IFERROR(ROUND(XLOOKUP($B$5,DATA!$A:$A,DATA!$AB:$AB,0)-XLOOKUP($H$5,DATA!$A:$A,DATA!$AB:$AB,0),1),"--") | J17: =IFERROR(ROUND(XLOOKUP($B$5,DATA!$A:$A,DATA!$AC:$AC,0)-XLOOKUP($H$5,DATA!$A:$A,DATA!$AC:$AC,0),1),"--") | L17: P1 - P2
B18: RADAR | Percentile scores (0 - 100) | H18: METRICS | Values per 90 min
B50: Player 1 | E50: Radar = percentile vs all players in DB | H50: Player 2
B51: Football Successor 2026 | Source: mart.player_profile_merged_v1 | Atualizar: Dados -> Atualizar Tudo

Sheet DATA
A1: INSTRUCOES | Exporta o CSV do Supabase com a query abaixo. No Excel: Dados -> Obter Dados -> Do Ficheiro -> Do CSV -> carregar nesta sheet substituindo os dados existentes (linha 10 em diante).
A2: SELECT
A3: name, age, club, positions, nationality, rating_merged,
A4: goals_p90_merged, assists_p90_merged, xg_per_90_merged, shots_p90_merged,
A5: key_passes_p90_merged, passes_p90_merged, accurate_crosses_p90_merged,
A6: interceptions_p90_merged, tackles_p90_merged, blocks_p90_merged,
A7: dribbles_won_p90_merged, aerial_won_p90_merged, pass_success_pct_merged,
A8: dispossessed_p90_merged, turnovers_p90_merged,
A9: goals_p90_pct_merged, assists_p90_pct_merged, xg_per_90_pct_merged,
A10: key_passes_p90_pct_merged, tackles_p90_pct_merged, interceptions_p90_pct_merged,
A11: pass_success_pct_pct_merged, dribbles_won_p90_pct_merged, aerial_won_p90_pct_merged
A12: FROM mart.player_profile_merged_v1
... A14: ORDER BY name ASC;
A17: name | B17: age | C17: club | D17: positions | E17: nationality | F17: rating_merged | G17: goals_p90_merged | H17: assists_p90_merged | I17: xg_per_90_merged | J17: shots_p90_merged | K17: key_passes_p90_merged | L17: passes_p90_merged | M17: accurate_crosses_p90_merged | N17: interceptions_p90_merged | O17: tackles_p90_merged | P17: blocks_p90_merged | Q17: dribbles_won_p90_merged | R17: aerial_won_p90_merged | S17: pass_success_pct_merged | T17: dispossessed_p90_merged | U17: turnovers_p90_merged | V17: goals_p90_pct_merged | W17: assists_p90_pct_merged | X17: xg_per_90_pct_merged | Y17: key_passes_p90_pct_merged | Z17: tackles_p90_pct_merged | AA17: interceptions_p90_pct_merged | AB17: pass_success_pct_pct_merged | AC17: dribbles_won_p90_pct_merged | AD17: aerial_won_p90_pct_merged
A18: -- DADOS DO SUPABASE ABAIXO --
A19: Aaron Appindangoyé | B19: 34 | C19: Sivasspor | D19: D(C) | E19: ga | F19: 6.5543918 | G19: 0.023622047 | H19: 0.023622047 | I19: 0.033288543 | J19: 0.39685039 | K19: 0.15826772 | L19: 39.364961 | M19: 0 | N19: 1.0523622 | O19: 0.5007874 | P19: 0.94251969 | Q19: 0.087401575 | R19: 1.7751969 | S19: 81.716333 | T19: 0.1511811 | U19: 0.28937008 | V19: 22.97 | W19: 21.33 | X19: 21.68 | Y19: 5.67 | Z19: 3.87 | AA19: 57.65 | AB19: 53.3 | AC19: 4.53 | AD19: 71.36
A20: Aaron Cresswell | B20: 36 | C20: Stoke | D20: D(CL),M(L) | E20: gb-eng | F20: 6.674155 | G20: 0.022447689 | H20: 0.095402678 | I20: 0.024805819 | J20: 0.53313261 | K20: 1.1977445 | L20: 50.752621 | M20: 1.3067762 | N20: 1.0494295 | O20: 0.95322507 | P20: 0.40004988 | Q20: 0.14911679 | R20: 1.1095572 | S20: 82.777341 | T20: 0.14270316 | U20: 0.49545256 | V20: 15.82 | W20: 59.87 | X20: 14.98 | Y20: 67.68 | Z20: 21.5 | AA20: 62.07 | AB20: 65.4 | AC20: 11.15 | AD20: 44.76
A21: Aaron Donnelly | B21: 22 | C21: Dundee FC | D21: D(C) | E21: gb-nir | F21: 6.6717647 | G21: 0 | H21: 0.13274336 | I21: 0.036338496 | J21: 0.79646018 | K21: 0.59734513 | L21: 41.150442 | M21: 0.26548673 | N21: 0.86283186 | O21: 0.7300885 | P21: 0.79646018 | Q21: 0 | R21: 3.5840708 | S21: 61.612903 | T21: 0 | U21: 0.26548673 | V21: 0 | W21: 72.29 | X21: 8.43 | Y21: 30.12 | Z21: 12.05 | AA21: 63.86 | AB21: 6.02 | AC21: 0 | AD21: 81.93
A22: Aaron Hickey | B22: 23 | C22: Brentford | D22: D(LR),M(LR) | E22: gb-sct | F22: 6.5859748 | G22: 0.088118413 | H22: 0.038357427 | I22: 0.0076631918 | J22: 0.59816852 | K22: 0.12440247 | L22: 15.073432 | M22: 0.082934977 | N22: 0.35247365 | O22: 0.78788228 | P22: 0.14513621 | Q22: 0.35247365 | R22: 0.6074987 | S22: 83.795749 | T22: 0.26953867 | U22: 0.33173991 | V22: 35.48 | W22: 33.55 | X22: 6.15 | Y22: 7.03 | Z22: 24.62 | AA22: 18.81 | AB22: 64.02 | AC22: 23.74 | AD22: 25.1
A23: Aarón Martín | B23: 28 | C23: Genoa | D23: D(L),M(L) | E23: es | F23: 6.7624897 | G23: 0.051703731 | H23: 0.1688158 | I23: 0.027211425 | J23: 0.50769327 | K23: 2.002118 | L23: 32.50732 | M23: 2.2525385 | N23: 0.59428144 | O23: 1.8906123 | P23: 0.26537096 | Q23: 0.52451255 | R23: 0.44041612 | S23: 79.329521 | T23: 0.53510247 | U23: 0.76683486 | V23: 22.94 | W23: 73.91 | X23: 12.86 | Y23: 89.91 | Z23: 69.77 | AA23: 36.79 | AB23: 37.69 | AC23: 45.49 | AD23: 14.75
A24: Aaron Opoku | B24: 26 | C24: Kayserispor | D24: D(R),M(LR) | E24: gh | F24: 6.3536842 | G24: 0 | H24: 0.1453958 | I24: 0.064359451 | J24: 0.9450727 | K24: 1.5266559 | L24: 23.045234 | M24: 0.8723748 | N24: 0.5088853 | O24: 1.0177706 | P24: 0.0726979 | Q24: 1.2358643 | R24: 1.0177706 | S24: 76.656151 | T24: 0.9450727 | U24: 1.453958 | V24: 0 | W24: 76.6 | X24: 38.83 | Y24: 82.98 | Z24: 25.53 | AA24: 28.72 | AB24: 23.4 | AC24: 84.04 | AD24: 49.47
A25: Aaron Ramsey | B25: 23 | C25: Norwich | D25: AM(CL) | E25: gb-eng | F25: 6.6338889 | G25: 0.25911708 | H25: 0.25911708 | I25: null | J25: 1.4683301 | K25: 1.8138196 | L25: 37.744722 | M25: 0.086372361 | N25: 0.25911708 | O25: 1.2092131 | P25: 0.086372361 | Q25: 0.69097889 | R25: 0.51823417 | S25: 80.778032 | T25: 1.0364683 | U25: 2.159309 | V25: 82.11 | W25: 97.15 | X25: 7.32 | Y25: 92.68 | Z25: 29.67 | AA25: 9.76 | AB25: 71.54 | AC25: 54.07 | AD25: 12.6
A26: Aaron Wan-Bissaka | B26: 28 | C26: West Ham | D26: D(LR),M(R) | E26: cd | F26: 6.9246483 | G26: 0.021340251 | H26: 0.096031132 | I26: 0.02354652 | J26: 0.29123167 | K26: 0.8448229 | L26: 40.866582 | M26: 0.46760257 | N26: 1.8515806 | O26: 1.9520054 | P26: 0.43747516 | Q26: 1.2935958 | R26: 0.86616315 | S26: 81.18122 | T26: 0.58622926 | U26: 1.0249597 | V26: 15.94 | W26: 52.88 | X26: 37.91 | Y26: 50.92 | Z26: 61.85 | AA26: 96.38 | AB26: 41.63 | AC26: 76.31 | AD26: 38.24
A27: Aaron Zehnter | B27: 21 | C27: Wolfsburg | D27: D(L),M(L) | E27: de | F27: 6.535 | G27: 0.14863749 | H27: 0 | I27: 0.057344344 | J27: 0.59454996 | K27: 1.1147812 | L27: 37.382329 | M27: 0.89182494 | N27: 1.1890999 | O27: 0.89182494 | P27: 0.44591247 | Q27: 0.29727498 | R27: 0.59454996 | S27: 78.926441 | T27: 0 | U27: 0.59454996 | V27: 60.89 | W27: 0 | X27: 29.21 | Y27: 60.89 | Z27: 13.86 | AA27: 74.75 | AB27: 38.12 | AC27: 30.69 | AD27: 23.76
A28: Abakar Sylla | B28: 23 | C28: Strasbourg | D28: D(C) | E28: ci | F28: 6.5376508 | G28: 0.072106825 | H28: 0 | I28: 0.05851776 | J28: 0.55148368 | K28: 0.1962908 | L28: 63.112166 | M28: 0 | N28: 1.3700297 | O28: 2.451632 | P28: 0.72240356 | Q28: 0.52744807 | R28: 1.8400593 | S28: 87.848434 | T28: 0.37789318 | U28: 0.73175074 | V28: 41.33 | W28: 0 | X28: 37.02 | Y28: 8.81 | Z28: 78.09 | AA28: 74.85 | AB28: 86.65 | AC28: 33.93 | AD28: 76.91
A29: Abdallah Sima | B29: 24 | C29: Brest | D29: AM(LR),FW | E29: sn | F29: 6.7116313 | G29: 0.45978639 | H29: 0.10191739 | I29: 0.44652543 | J29: 2.8872732 | K29: 0.97400592 | L29: 22.135761 | M29: 0.15750869 | N29: 0.1667739 | O29: 1.2554369 | P29: 0.062540214 | Q29: 1.0898211 | R29: 3.1235362 | S29: 72.188452 | T29: 1.6422597 | U29: 3.6574443 | V29: 90.62 | W29: 55.01 | X29: 89.76 | Y29: 54.09 | Z29: 31.05 | AA29: 9.01 | AB29: 22.17 | AC29: 60.55 | AD29: 89.59
A30: Abde Ezzalzouli | B30: 24 | C30: Real Betis | D30: AM(L) | E30: ma | F30: 6.8327485 | G30: 0.21410595 | H30: 0.16001603 | I30: 0.37450996 | J30: 2.8329598 | K30: 1.0671491 | L30: 30.523621 | M30: 0.35834575 | N30: 0.42257754 | O30: 1.8649755 | P30: 0.057470545 | Q30: 2.3303742 | R30: 1.0186936 | S30: 76.506853 | T30: 2.1207758 | U30: 3.2949779 | V30: 71.53 | W30: 72.19 | X30: 87.18 | Y30: 64.16 | Z30: 63.91 | AA30: 22.7 | AB30: 20.82 | AC30: 94.42 | AD30: 45.93
A31: Abdel Abqar | B31: 26 | C31: Getafe | D31: D(C) | E31: ma | F31: 6.5578236 | G31: 0 | H31: 0.036007785 | I31: 0.035612576 | J31: 0.47102076 | K31: 0.23161765 | L31: 31.132137 | M31: 0.033088235 | N31: 1.231077 | O31: 1.5979671 | P31: 0.72988754 | Q31: 0.12943339 | R31: 1.5376298 | S31: 74.519649 | T31: 0.082720588 | U31: 0.65787197 | V31: 0 | W31: 26.94 | X31: 22.12 | Y31: 11.68 | Z31: 47.33 | AA31: 81.13 | AB31: 16.72 | AC31: 9.22 | AD31: 67.87
A32: Abdelhamid Sabiri | B32: 29 | C32: Sampdoria | D32: AM(CL),FW | E32: ma | F32: 6.4427778 | G32: 0.16806723 | H32: 0 | I32: 0.27890756 | J32: 2.7731092 | K32: 1.1764706 | L32: 33.781513 | M32: 0.84033613 | N32: 0.16806723 | O32: 1.512605 | P32: 0.33613445 | Q32: 1.1764706 | R32: 2.5210084 | S32: 74.129353 | T32: 2.3529412 | U32: 2.8571429 | V32: 69.73 | W32: 0 | X32: 83.24 | Y32: 68.11 | Z32: 48.65 | AA32: 7.03 | AB32: 17.3 | AC32: 75.68 | AD32: 85.41
A33: Abdelkahar Kadri | B33: 25 | C33: Gent | D33: AM(CLR),FW | E33: dz | F33: 6.9378883 | G33: 0.11128166 | H33: 0.21949348 | I33: 0.099500384 | J33: 1.5464313 | K33: 1.6469685 | L33: 45.594781 | M33: 0.85878741 | N33: 0.96239447 | O33: 2.2547966 | P33: 0.11358404 | Q33: 2.1603991 | R33: 0.47122026 | S33: 83.428985 | T33: 1.7198772 | U33: 2.1174213 | V33: 49.82 | W33: 79.2 | X33: 42.76 | Y33: 83.83 | Z33: 70.92 | AA33: 48.77 | AB33: 71.98 | AC33: 90.65 | AD33: 17.53
A34: Abdón Prats | B34: 33 | C34: Mallorca | D34: FW | E34: es | F34: 6.3979412 | G34: 0.42891183 | H34: 0.071485306 | I34: 0.27798491 | J34: 2.3590151 | K34: 1.0007943 | L34: 16.513106 | M34: 0.071485306 | N34: 0.14297061 | O34: 0.42891183 | P34: 0.21445592 | Q34: 0.57188245 | R34: 2.9308975 | S34: 56.709957 | T34: 0.71485306 | U34: 2.9308975 | V34: 92.41 | W34: 47.77 | X34: 81.7 | Y34: 61.16 | Z34: 4.46 | AA34: 5.8 | AB34: 0.45 | AC34: 44.2 | AD34: 92.41
A35: Abdou Harroui | B35: 28 | C35: Frosinone | D35: M(CLR) | E35: nl | F35: 6.6394444 | G35: 0.26264591 | H35: 0.26264591 | I35: 0.3287714 | J35: 2.8891051 | K35: 1.4007782 | L35: 31.605058 | M35: 0.35019455 | N35: 0.43774319 | O35: 2.0136187 | P35: 0.26264591 | Q35: 1.6634241 | R35: 1.0505837 | S35: 81.717452 | T35: 0.61284047 | U35: 2.4513619 | V35: 80.82 | W35: 93.88 | X35: 88.16 | Y35: 77.14 | Z35: 81.63 | AA35: 31.02 | AB35: 47.76 | AC35: 90.61 | AD35: 45.31
A36: Abdoul Ouattara | B36: 20 | C36: Strasbourg | D36: M(R) | E36: fr | F36: 6.3957895 | G36: 0.15915119 | H36: 0 | I36: 0.12646437 | J36: 1.193634 | K36: 0.30238727 | L36: 38.629973 | M36: 0.22679045 | N36: 0.68037135 | O36: 1.3607427 | P36: 0 | Q36: 0.37798408 | R36: 0 | S36: 89.194915 | T36: 0.37798408 | U36: 1.4363395 | V36: 68.75 | W36: 0 | X36: 64.06 | Y36: 17.19 | Z36: 36.98 | AA36: 34.38 | AB36: 80.73 | AC36: 33.33 | AD36: 0
A37: Abdoulaye Bamba | B37: 35 | C37: Angers | D37: D(CLR),M(R) | E37: ci | F37: 6.3052238 | G37: 0 | H37: 0 | I37: 0.0093134295 | J37: 0.03375654 | K37: 0.31731148 | L37: 37.525458 | M37: 0.22110534 | N37: 1.1578493 | O37: 1.3738912 | P37: 0.3561315 | Q37: 0.18228532 | R37: 0.85910395 | S37: 89.323607 | T37: 0.2497984 | U37: 0.35950715 | V37: 0 | W37: 0 | X37: 47.83 | Y37: 18.25 | Z37: 31.46 | AA37: 69.48 | AB37: 86.22 | AC37: 8.92 | AD37: 44.7
... A64: Adam Masina | B64: 32 | C64: Torino | D64: D(CL),M(L) | E64: ma | F64: 6.6021252 | G64: 0.025411167 | H64: 0.06861015 | I64: 0.042253434 | J64: 0.40022588 | K64: 0.29095786 | L64: 52.242818 | M64: 0.2439472 | N64: 1.2438766 | O64: 1.6326675 | P64: 0.61749135 | Q64: 0.33415684 | R64: 2.7189948 | S64: 82.510641 | T64: 0.3506741 | U64: 0.56921014 | V64: 20.25 | W64: 44.35 | X64: 25.8 | Y64: 13.22 | Z64: 54.44 | AA64: 86.25 | AB64: 55.21 | AC64: 28.14 | AD64: 87.06
A65: Adam Montgomery | B65: 23 | C65: St. Johnstone | D65: D(L),M(L) | E65: gb-sct | F65: 6.5908696 | G65: 0 | H65: 0.048465267 | I65: null | J65: 0.2907916 | K65: 0.53311793 | L65: 27.431341 | M65: 0.1453958 | N65: 0.96930533 | O65: 1.5993538 | P65: 0.2907916 | Q65: 1.1631664 | R65: 0.726979 | S65: 72.438163 | T65: 0.96930533 | U65: 1.1631664 | V65: 0 | W65: 41.67 | X65: 0 | Y65: 27.78 | Z65: 48.61 | AA65: 58.33 | AB65: 40.28 | AC65: 90.28 | AD65: 15.28
A66: Adam Obert | B66: 23 | C66: Cagliari | D66: D(CL),M(L) | E66: sk | F66: 6.548235 | G66: 0.022552069 | H66: 0.07561576 | I66: 0.05425803 | J66: 0.36481288 | K66: 0.66807187 | L66: 40.685259 | M66: 0.41893784 | N66: 1.8001857 | O66: 2.1610188 | P66: 0.64445853 | Q66: 0.42318294 | R66: 1.4340463 | S66: 79.986984 | T66: 0.37330307 | U66: 1.1865041 | V66: 13.95 | W66: 50.57 | X66: 27.77 | Y66: 36.22 | Z66: 81.37 | AA66: 97.77 | AB66: 34.37 | AC66: 43.57 | AD66: 56.72
A67: Adam Randell | B67: 25 | C67: Bristol City | D67: DMC | E67: gb-eng | F67: 6.6830252 | G67: 0.058256617 | H67: 0.058256617 | I67: 0.047467297 | J67: 0.85325348 | K67: 1.0917441 | L67: 40.779968 | M67: 0.5532277 | N67: 1.1704284 | O67: 1.5587218 | P67: 0.65133083 | Q67: 0.46260629 | R67: 1.4281698 | S67: 78.301164 | T67: 0.65578624 | U67: 1.2050629 | V67: 38.28 | W67: 43.06 | X67: 25.64 | Y67: 62.92 | Z67: 53.92 | AA67: 75.27 | AB67: 44.34 | AC67: 43.4 | AD67: 52.62
A68: Adam Smith | B68: 34 | C68: Bournemouth | D68: D(LR),M(LR) | E68: gb-eng | F68: 6.4525657 | G68: 0 | H68: 0.048901274 | I68: 0.011520721 | J68: 0.16067561 | K68: 0.57773362 | L68: 33.138297 | M68: 0.52813376 | N68: 0.81874704 | O68: 1.6151392 | P68: 0.35069199 | Q68: 0.23612329 | R68: 0.90467356 | S68: 77.79059 | T68: 0.31995405 | U68: 0.69160373 | V68: 0 | W68: 34.15 | X68: 12.11 | Y68: 33.21 | Z68: 47.04 | AA68: 48.49 | AB68: 29.59 | AC68: 17.32 | AD68: 39.31
A69: Adam Wharton | B69: 22 | C69: Crystal Palace | D69: DMC | E69: gb-eng | F69: 6.7667545 | G69: 0.036627651 | H69: 0.16775464 | I69: 0.038274724 | J69: 0.91422618 | K69: 1.457048 | L69: 46.441664 | M69: 0.70251835 | N69: 1.2402123 | O69: 2.6599 | P69: 0.193394 | Q69: 0.45564798 | R69: 0.71570431 | S69: 80.975043 | T69: 0.91788894 | U69: 1.17355 | V69: 17.96 | W69: 78.51 | X69: 20.01 | Y69: 79.5 | Z69: 87.5 | AA69: 77.42 | AB69: 44.06 | AC69: 38.28 | AD69: 27.61
A70: Adama Boiro | B70: 23 | C70: Athletic Club | D70: D(L) | E70: es | F70: 6.3861111 | G70: 0 | H70: 0 | I70: 0.026861538 | J70: 0.40723982 | K70: 0.40723982 | L70: 30.298643 | M70: 0.32579186 | N70: 0.97737557 | O70: 1.6289593 | P70: 0.24434389 | Q70: 0.65158371 | R70: 1.3846154 | S70: 83.870968 | T70: 1.2217195 | U70: 1.8733032 | V70: 0 | W70: 0 | X70: 17.44 | Y70: 23.26 | Z70: 54.26 | AA70: 63.57 | AB70: 57.36 | AC70: 51.16 | AD70: 65.89
A71: Adama Camara | B71: 29 | C71: Paris FC | D71: M(C) | E71: fr | F71: 6.4894737 | G71: 0.061141304 | H71: 0 | I71: 0.10603736 | J71: 0.91711957 | K71: 0.55027174 | L71: 39.619565 | M71: 0 | N71: 1.1005435 | O71: 2.0788043 | P71: 0.48913043 | Q71: 0.42798913 | R71: 1.1005435 | S71: 87.962963 | T71: 0.67255435 | U71: 1.6508152 | V71: 47.92 | W71: 0 | X71: 57.81 | Y71: 34.38 | Z71: 73.96 | AA71: 66.15 | AB71: 76.04 | AC71: 39.58 | AD71: 61.46
A72: Adama Traoré | B72: 30 | C72: Fulham | D72: M(CLR),FW | E72: es | F72: 6.6354491 | G72: 0.10465946 | H72: 0.18672199 | I72: 0.20975159 | J72: 1.6947697 | K72: 1.7839681 | L72: 24.763855 | M72: 1.2678066 | N72: 0.11774189 | O72: 0.89198404 | P72: 0.036868674 | Q72: 3.6559452 | R72: 1.6329254 | S72: 78.175434 | T72: 1.6234109 | U72: 2.8388879 | V72: 58.06 | W72: 60.47 | X72: 70.58 | Y72: 87.5 | Z72: 15.34 | AA72: 3.21 | AB72: 26.68 | AC72: 99.04 | AD72: 67.75
A73: Adem Zorgane | B73: 26 | C73: Union St.Gilloise | D73: DMC | E73: dz | F73: 7.0532277 | G73: 0.08302002 | H73: 0.19753039 | I73: 0.04697914 | J73: 1.0563582 | K73: 2.0491631 | L73: 71.861557 | M73: 0.92123595 | N73: 1.0546405 | O73: 2.3972747 | P73: 0.32578201 | Q73: 0.89947898 | R73: 0.86283566 | S73: 83.745713 | T73: 1.10388 | U73: 1.2996927 | V73: 44.31 | W73: 81.4 | X73: 26.7 | Y73: 89.11 | Z73: 78.72 | AA73: 54.32 | AB73: 76.86 | AC73: 61.17 | AD73: 37.65
A74: Ademir | B74: 31 | C74: Bahia | D74: AM(CR),FW | E74: br | F74: 6.7886572 | G74: 0.22513837 | H74: 0.16904077 | I74: 0.21517312 | J74: 2.4353839 | K74: 1.6799362 | L74: 25.676994 | M74: 1.0778219 | N74: 0.41287835 | O74: 1.6103751 | P74: 0.026926849 | Q74: 2.267839 | R74: 0.66494357 | S74: 79.176527 | T74: 1.3074481 | U74: 2.6500507 | V74: 73.78 | W74: 66.84 | X74: 72.1 | Y74: 83.26 | Z74: 50.95 | AA74: 20.35 | AB74: 28.24 | AC74: 93.31 | AD74: 28.21
A75: Ademola Lookman | B75: 28 | C75: Atalanta | D75: AM(CLR),FW | E75: ng | F75: 7.0270773 | G75: 0.56041275 | H75: 0.2310273 | I75: 0.49439384 | J75: 2.8920348 | K75: 2.1875159 | L75: 32.790627 | M75: 0.9576577 | N75: 0.28897474 | O75: 1.154374 | P75: 0.0083871296 | Q75: 1.7513851 | R75: 0.56498755 | S75: 79.151638 | T75: 2.2492757 | U75: 2.9499822 | V75: 97.33 | W75: 80.51 | X75: 95.51 | Y75: 94.64 | Z75: 29.04 | AA75: 15.69 | AB75: 34.68 | AC75: 92.14 | AD75: 21.95
A76: Aderlan | B76: 35 | C76: Sport Recife | D76: D(R),M(R) | E76: br | F76: 6.8315313 | G76: 0.029948422 | H76: 0.088181465 | I76: 0.0083548611 | J76: 0.60479175 | K76: 1.4258777 | L76: 40.450336 | M76: 0.93089679 | N76: 1.6371804 | O76: 2.8742166 | P76: 0.35522156 | Q76: 0.6738395 | R76: 1.5648051 | S76: 77.420843 | T76: 0.59397704 | U76: 1.1513505 | V76: 21.86 | W76: 52.03 | X76: 8.42 | Y76: 68.84 | Z76: 86.8 | AA76: 90.33 | AB76: 20.91 | AC76: 38.66 | AD76: 68.8
A77: Aderllan Santos | B77: 36 | C77: Rio Ave | D77: D(C) | E77: br | F77: 6.9371424 | G77: 0.048916315 | H77: 0 | I77: 0.035649609 | J77: 0.6577363 | K77: 0.15728477 | L77: 55.256623 | M77: 0 | N77: 1.480283 | O77: 1.9762191 | P77: 0.96177002 | Q77: 0.085039133 | R77: 3.1697772 | S77: 86.694562 | T77: 0.046658639 | U77: 0.25737508 | V77: 28.05 | W77: 0 | X77: 26.65 | Y77: 6.99 | Z77: 68.76 | AA77: 86.72 | AB77: 80.75 | AC77: 3.54 | AD77: 98.24
... A118: Ajdin Hrustic | B118: 29 | C118: Heracles | D118: M(CLR) | E118: ro | F118: 6.5331761 | G118: 0.084358372 | H118: 0.15573853 | I118: 0.076498637 | J118: 1.7390803 | K118: 1.7286977 | L118: 43.471816 | M118: 1.4963877 | N118: 0.49966112 | O118: 1.4263054 | P118: 0.26215986 | Q118: 0.73975803 | R118: 0.32705092 | S118: 82.427214 | T118: 0.90328349 | U118: 1.6092982 | V118: 38.15 | W118: 47.86 | X118: 37.24 | Y118: 77.06 | Z118: 43.92 | AA118: 26.31 | AB118: 60.52 | AC118: 56.06 | AD118: 9.38
A119: Aji Alese | B119: 25 | C119: Sunderland | D119: D(CL) | E119: gb-eng | F119: 6.8425 | G119: 0.06378455 | H119: 0 | I119: null | J119: 0.70163005 | K119: 0.70163005 | L119: 39.099929 | M119: 0.31892275 | N119: 1.8497519 | O119: 2.1686747 | P119: 0.5102764 | Q119: 0.31892275 | R119: 2.1686747 | S119: 79.608483 | T119: 0.3827073 | U119: 0.7654146 | V119: 45.53 | W119: 0 | X119: 7.32 | Y119: 41.87 | Z119: 76.83 | AA119: 95.12 | AB119: 64.23 | AC119: 22.36 | AD119: 69.51
A120: Akin Famewo | B120: 27 | C120: Sheff Wed | D120: D(CL) | E120: gb-eng | F120: 6.6592709 | G120: 0 | H120: 0.028411781 | I120: 0.0261127 | J120: 0.18609717 | K120: 0.22587366 | L120: 39.958329 | M120: 0.1690501 | N120: 1.6720333 | O120: 1.9320011 | P120: 0.5852827 | Q120: 0.72876219 | R120: 2.288569 | S120: 74.863192 | T120: 0.4673738 | U120: 0.93474761 | V120: 0 | W120: 19.61 | X120: 10.42 | Y120: 9.8 | Z120: 70.61 | AA120: 88.11 | AB120: 25.24 | AC120: 52.59 | AD120: 78.24
A121: Akor Adams | B121: 26 | C121: Sevilla | D121: FW | E121: ng | F121: 6.5627333 | G121: 0.33348172 | H121: 0.10723264 | I121: 0.49950401 | J121: 2.7904054 | K121: 0.66224992 | L121: 14.673196 | M121: 0.056562271 | N121: 0.10251912 | O121: 0.3959359 | P121: 0.10016235 | Q121: 0.58329842 | R121: 2.2059286 | S121: 64.746532 | T121: 1.1995915 | U121: 2.2672044 | V121: 86.09 | W121: 54.32 | X121: 94.17 | Y121: 36.75 | Z121: 2.99 | AA121: 3.58 | AB121: 1.17 | AC121: 42.91 | AD121: 86.89
A122: Al Musrati | B122: 29 | C122: Besiktas | D122: DMC | E122: ly | F122: 7.0037561 | G122: 0.077306305 | H122: 0.056388128 | I122: 0.019282921 | J122: 0.87219701 | K122: 0.93495154 | L122: 61.927807 | M122: 0.030922522 | N122: 1.7925968 | O122: 2.2955425 | P122: 0.3883505 | Q122: 0.29831139 | R122: 1.6297988 | S122: 84.535746 | T122: 0.67120062 | U122: 0.93586103 | V122: 47.35 | W122: 30.85 | X122: 20.72 | Y122: 49.64 | Z122: 79.85 | AA122: 90.32 | AB122: 72.53 | AC122: 17.19 | AD122: 72.8
A123: Alan | B123: 25 | C123: Moreirense | D123: AM(C) | E123: null | F123: 6.7282781 | G123: 0.15643376 | H123: 0.20079557 | I123: 0.14487214 | J123: 1.4857316 | K123: 2.0274127 | L123: 37.90211 | M123: 0.84520927 | N123: 0.24437911 | O123: 1.1456244 | P123: 0.081719128 | Q123: 0.78528191 | R123: 0.13853338 | S123: 86.608748 | T123: 1.3370806 | U123: 1.9597025 | V123: 66.36 | W123: 85.18 | X123: 60.69 | Y123: 91.87 | Z123: 25.93 | AA123: 11.14 | AB123: 79.9 | AC123: 57.21 | AD123: 2.99
A124: Alan Browne | B124: 30 | C124: Middlesbrough | D124: D(R),M(CR) | E124: ie | F124: 6.7746764 | G124: 0.10331805 | H124: 0.081010743 | I124: 0.064766563 | J124: 1.0907099 | K124: 0.97212891 | L124: 40.968541 | M124: 0.43264433 | N124: 1.2180963 | O124: 1.9695003 | P124: 0.37100572 | Q124: 0.95745305 | R124: 1.946606 | S124: 77.7874 | T124: 1.0402249 | U124: 2.1238903 | V124: 54.88 | W124: 50.84 | X124: 37.35 | Y124: 57.61 | Z124: 70.7 | AA124: 70.39 | AB124: 45.13 | AC124: 70.8 | AD124: 64.26
A125: Alan Forrest | B125: 29 | C125: Hearts | D125: M(CLR),FW | E125: gb-sct | F125: 6.6329167 | G125: 0.19749529 | H125: 0.14163804 | I125: 0.11633869 | J125: 2.7459825 | K125: 1.1819794 | L125: 29.464701 | M125: 0.78698881 | N125: 0.43887842 | O125: 1.3076582 | P125: 0.056854705 | Q125: 1.342569 | R125: 0.6772692 | S125: 75.227559 | T125: 1.7784551 | U125: 2.4607115 | V125: 73.39 | W125: 64.09 | X125: 32.51 | Y125: 62.8 | Z125: 42.12 | AA125: 21.34 | AB125: 55.07 | AC125: 90.55 | AD125: 14.18
A126: Alan Franco | B126: 29 | C126: Sao Paulo | D126: D(C) | E126: ar | F126: 6.5762454 | G126: 0.012734862 | H126: 0.028198623 | I126: 0.039441597 | J126: 0.43298531 | K126: 0.23741422 | L126: 62.741027 | M126: 0 | N126: 0.82412751 | O126: 1.1988963 | P126: 0.64311054 | Q126: 0.48847293 | R126: 1.7701458 | S126: 89.843605 | T126: 0.22740825 | U126: 0.60399632 | V126: 7.66 | W126: 21.74 | X126: 26.1 | Y126: 11.66 | Z126: 28.01 | AA126: 51.78 | AB126: 86.9 | AC126: 36.76 | AD126: 72.96
A127: Alan Franco | B127: 27 | C127: Atletico MG | D127: M(CR) | E127: ec | F127: 6.5761884 | G127: 0.022402828 | H127: 0 | I127: 0.031784012 | J127: 0.41109189 | K127: 0.53878801 | L127: 42.896935 | M127: 0.060487635 | N127: 1.1481449 | O127: 1.6914135 | P127: 0.24307068 | Q127: 0.086250887 | R127: 1.013728 | S127: 89.679845 | T127: 0.24867139 | U127: 0.54550886 | V127: 21.06 | W127: 0 | X127: 18.97 | Y127: 26.8 | Z127: 56.54 | AA127: 74.62 | AB127: 88.89 | AC127: 6.27 | AD127: 45.52
A128: Alan Minda | B128: 22 | C128: Cercle Bruges | D128: AM(CLR),FW | E128: ec | F128: 6.5688366 | G128: 0.250294 | H128: 0.18164193 | I128: 0.25914139 | J128: 2.3999619 | K128: 1.3058195 | L128: 20.531259 | M128: 0.36185361 | N128: 0.18307218 | O128: 0.48056447 | P128: 0.024314274 | Q128: 1.9952007 | R128: 1.012618 | S128: 75.019076 | T128: 1.6362076 | U128: 3.1508438 | V128: 71.43 | W128: 75.19 | X128: 78.38 | Y128: 71.84 | Z128: 4.14 | AA128: 9.03 | AB128: 31.59 | AC128: 93.68 | AD128: 42.01
A129: Alan Patrick | B129: 34 | C129: Internacional | D129: M(CLR),FW | E129: br | F129: 7.0696282 | G129: 0.32436345 | H129: 0.20696831 | I129: 0.2662973 | J129: 2.0086105 | K129: 3.2823138 | L129: 42.448861 | M129: 1.4671 | N129: 0.20764689 | O129: 0.96494733 | P129: 0.084823078 | Q129: 1.6048526 | R129: 0.32572062 | S129: 85.566653 | T129: 2.1545062 | U129: 2.1843639 | V129: 87.56 | W129: 86.3 | X129: 79.13 | Y129: 98.48 | Z129: 19.85 | AA129: 8.99 | AB129: 65.09 | AC129: 84.43 | AD129: 8.54
A130: Alan Rodríguez | B130: 26 | C130: Internacional | D130: M(C) | E130: null | F130: 6.5553333 | G130: 0 | H130: 0.095338983 | I130: 0.11234746 | J130: 1.0487288 | K130: 1.1440678 | L130: 38.42161 | M130: 0.28601695 | N130: 0.85805085 | O130: 3.2415254 | P130: 0.28601695 | Q130: 1.3347458 | R130: 0.76271186 | S130: 83.622829 | T130: 2.1927966 | U130: 2.1927966 | V130: 0 | W130: 65.27 | X130: 59.81 | Y130: 69.13 | Z130: 97.11 | AA130: 57.56 | AB130: 44.69 | AC130: 84.57 | AD130: 36.33
A131: Alan Ruschel | B131: 36 | C131: Juventude | D131: D(L),M(LR) | E131: br | F131: 6.4618427 | G131: 0.024370042 | H131: 0.024370042 | I131: 0.019793778 | J131: 0.3010417 | K131: 1.0636807 | L131: 35.089994 | M131: 0.94899812 | N131: 1.2830111 | O131: 2.4843108 | P131: 0.40712306 | Q131: 0.41572425 | R131: 0.90885923 | S131: 83.735638 | T131: 0.66372527 | U131: 1.0149406 | V131: 20.27 | W131: 21.44 | X131: 9.79 | Y131: 60.44 | Z131: 82.55 | AA131: 79.76 | AB131: 48.22 | AC131: 34.25 | AD131: 39.71
... A169: Álex Baena | B169: 24 | C169: Villarreal | D169: AM(CL),FW | E169: es | F169: 6.993621 | G169: 0.18786256 | H169: 0.32475465 | I169: 0.24881835 | J169: 2.5550764 | K169: 2.7392982 | L169: 36.606985 | M169: 1.7963447 | N169: 0.55266543 | O169: 1.1344568 | P169: 0.084465336 | Q169: 0.90290532 | R169: 0.36698732 | S169: 77.282981 | T169: 1.2211066 | U169: 1.846587 | V169: 70.11 | W169: 89.24 | X169: 78.94 | Y169: 94.74 | Z169: 24.93 | AA169: 34.11 | AB169: 29.42 | AC169: 63.81 | AD169: 15.63
A170: Alex Bangura | B170: 26 | C170: Cambuur | D170: D(L) | E170: sl | F170: 6.4915975 | G170: 0.070909394 | H170: 0.059923431 | I170: null | J170: 0.31559674 | K170: 0.50335682 | L170: 38.000444 | M170: 0.3016146 | N170: 0.8918604 | O170: 1.786717 | P170: 0.29262609 | Q170: 0.98873661 | R170: 0.30361205 | S170: 80.756261 | T170: 0.47739 | U170: 1.4521445 | V170: 34.04 | W170: 30.16 | X170: 14.79 | Y170: 19.43 | Z170: 56.3 | AA170: 47.36 | AB170: 56.19 | AC170: 61.8 | AD170: 7.09
A171: Alex Berenguer | B171: 30 | C171: Athletic Club | D171: D(LR),M(CLR),FW | E171: es | F171: 6.7383767 | G171: 0.20673916 | H171: 0.17452007 | I171: 0.2584602 | J171: 1.9707343 | K171: 1.9062961 | L171: 29.410659 | M171: 1.6794201 | N171: 0.4282454 | O171: 1.4793932 | P171: 0.063095718 | Q171: 1.2793664 | R171: 1.2968184 | S171: 75.189769 | T171: 1.8599812 | U171: 2.2586924 | V171: 74.06 | W171: 74.21 | X171: 79.17 | Y171: 92.53 | Z171: 42.95 | AA171: 23.45 | AB171: 18.73 | AC171: 78.63 | AD171: 55.61
A172: Alex Cochrane | B172: 25 | C172: Birmingham | D172: D(CL),M(L) | E172: null | F172: 6.7456733 | G172: 0.051646964 | H172: 0.15862996 | I172: 0.016672673 | J172: 0.51794527 | K172: 1.319211 | L172: 46.307406 | M172: 1.1059828 | N172: 0.85733961 | O172: 1.7700152 | P172: 0.30250365 | Q172: 0.42498073 | R172: 1.315522 | S172: 75.347603 | T172: 0.4603958 | U172: 0.82782706 | V172: 29.63 | W172: 77.66 | X172: 6.77 | Y172: 71.56 | Z172: 67.86 | AA172: 54.28 | AB172: 54.09 | AC172: 38.28 | AD172: 38.45
A173: Alex Gogic | B173: 31 | C173: St. Mirren | D173: D(C),DMC | E173: cy | F173: 6.61889 | G173: 0.044161239 | H173: 0.030852372 | I173: 0.075927447 | J173: 0.65152951 | K173: 0.27343671 | L173: 34.416124 | M173: 0.049000827 | N173: 1.186304 | O173: 1.3677885 | P173: 0.58377528 | Q173: 0.31275836 | R173: 2.4827086 | S173: 73.311462 | T173: 0.26436249 | U173: 0.77917364 | V173: 30.7 | W173: 29.95 | X173: 35.79 | Y173: 11.42 | Z173: 42.96 | AA173: 81.2 | AB173: 44.48 | AC173: 26.28 | AD173: 71.98
A174: Alex Iwobi | B174: 29 | C174: Fulham | D174: D(R),M(CLR) | E174: ng | F174: 6.8044041 | G174: 0.17570175 | H174: 0.14581699 | I174: 0.12724815 | J174: 1.5787395 | K174: 1.7523802 | L174: 41.405843 | M174: 0.73784429 | N174: 0.55080695 | O174: 1.377275 | P174: 0.053071202 | Q174: 1.2649495 | R174: 0.24989838 | S174: 81.343878 | T174: 1.0768817 | U174: 1.8002988 | V174: 67.24 | W174: 72.3 | X174: 56.25 | Y174: 87.38 | Z174: 36.11 | AA174: 28.59 | AB174: 42.87 | AC174: 77.33 | AD174: 5.74
A175: Álex Jiménez | B175: 20 | C175: Bournemouth | D175: D(R),M(R) | E175: es | F175: 6.6430017 | G175: 0.030537459 | H175: 0.02595684 | I175: 0.073417396 | J175: 0.96956433 | K175: 0.64739414 | L175: 32.175794 | M175: 0.44737378 | N175: 1.0306393 | O175: 2.2414495 | P175: 0.35270765 | Q175: 1.5910016 | R175: 0.60006107 | S175: 81.176113 | T175: 0.82603827 | U175: 1.586421 | V175: 22.61 | W175: 16.06 | X175: 35.42 | Y175: 39.18 | Z175: 78 | AA175: 71 | AB175: 36.65 | AC175: 92.69 | AD175: 21.79
A176: Alex Král | B176: 27 | C176: Espanyol | D176: M(C) | E176: cz | F176: 6.4156911 | G176: 0 | H176: 0.016292542 | I176: 0.068828249 | J176: 0.95637219 | K176: 0.39020637 | L176: 28.377534 | M176: 0.21913469 | N176: 0.80240768 | O176: 1.5469768 | P176: 0.3519189 | Q176: 0.80403693 | R176: 1.3881245 | S176: 73.475269 | T176: 0.87816799 | U176: 1.3970854 | V176: 0 | W176: 14.85 | X176: 36.48 | Y176: 21.05 | Z176: 48.42 | AA176: 48.49 | AB176: 17.85 | AC176: 60.06 | AD176: 58.74
A177: Alex Matos | B177: 21 | C177: Oxford | D177: M(C) | E177: gb-eng | F177: 6.4850494 | G177: 0.037747021 | H177: 0 | I177: 0.026118718 | J177: 0.50403375 | K177: 0.32862112 | L177: 23.425357 | M177: 0.1709718 | N177: 1.8185182 | O177: 3.7991266 | P177: 0.36636814 | Q177: 0.65724225 | R177: 1.0680187 | S177: 76.949898 | T177: 1.2145659 | U177: 2.0405595 | V177: 23.12 | W177: 0 | X177: 11.94 | Y177: 17.45 | Z177: 97.76 | AA177: 97.38 | AB177: 31.12 | AC177: 55.61 | AD177: 43.24
A178: Álex Moreno | B178: 32 | C178: Girona | D178: D(L),M(L) | E178: es | F178: 6.6891964 | G178: 0.052548427 | H178: 0.12905275 | I178: 0.076585468 | J178: 0.7696799 | K178: 0.78745363 | L178: 36.280825 | M178: 0.42811513 | N178: 1.0610146 | O178: 1.8059658 | P178: 0.29210743 | Q178: 1.1568382 | R178: 0.63135389 | S178: 80.307463 | T178: 0.55716788 | U178: 1.6715036 | V178: 20.99 | W178: 65.23 | X178: 41.98 | Y178: 46.31 | Z178: 54.42 | AA178: 67.04 | AB178: 38.82 | AC178: 73.18 | AD178: 25.36
A179: Alex Mowatt | B179: 31 | C179: WBA | D179: M(CLR) | E179: gb-eng | F179: 6.7845884 | G179: 0.098090763 | H179: 0.10942789 | I179: 0.04742294 | J179: 0.97104926 | K179: 1.5812822 | L179: 60.866058 | M179: 0.99027308 | N179: 0.84338339 | O179: 1.6133219 | P179: 0.40567185 | Q179: 0.28047057 | R179: 0.97893595 | S179: 87.462899 | T179: 0.36525254 | U179: 0.91091321 | V179: 49.34 | W179: 62.11 | X179: 30.97 | Y179: 85.56 | Z179: 56.81 | AA179: 47.92 | AB179: 88.81 | AC179: 23.43 | AD179: 34.38
A180: Alex Oxlade Chamberlain | B180: 32 | C180: Besiktas | D180: M(CLR) | E180: gb-eng | F180: 6.4831291 | G180: 0.21469815 | H180: 0.041475779 | I180: 0.20902548 | J180: 1.6639107 | K180: 0.75388327 | L180: 44.322969 | M180: 0.30496896 | N180: 0.65873296 | O180: 1.1540025 | P180: 0.31228822 | Q180: 1.2393939 | R180: 0.61237767 | S180: 85.770903 | T180: 1.0686112 | U180: 1.6712299 | V180: 66.92 | W180: 25.38 | X180: 68.3 | Y180: 40.16 | Z180: 28.04 | AA180: 34.96 | AB180: 78.21 | AC180: 62.24 | AD180: 23.1
A181: Alex Pinto | B181: 27 | C181: Gil Vicente | D181: D(R) | E181: pt | F181: 6.6421429 | G181: 0 | H181: 0 | I181: 0.032966387 | J181: 0.25210084 | K181: 0.50420168 | L181: 38.235294 | M181: 0.50420168 | N181: 1.2605042 | O181: 2.1008403 | P181: 0.084033613 | Q181: 0.42016807 | R181: 1.9327731 | S181: 75.824176 | T181: 0.25210084 | U181: 1.1764706 | V181: 0 | W181: 0 | X181: 16.92 | Y181: 23.08 | Z181: 75.38 | AA181: 83.08 | AB181: 23.08 | AC181: 33.08 | AD181: 81.54
A182: Alex Sandro | B182: 35 | C182: Flamengo | D182: D(CL),M(L) | E182: br | F182: 6.7080405 | G182: 0 | H182: 0.032352702 | I182: 0.013116934 | J182: 0.38718879 | K182: 0.44250148 | L182: 40.94391 | M182: 0.25882162 | N182: 0.64183587 | O182: 0.91318112 | P182: 0.32352702 | Q182: 0.60843953 | R182: 1.6186788 | S182: 87.598144 | T182: 0.44771966 | U182: 0.7952503 | V182: 0 | W182: 24.55 | X182: 6.09 | Y182: 23.42 | Z182: 27.46 | AA182: 42.29 | AB182: 81 | AC182: 45.05 | AD182: 65.72
... A241: Álvaro Núñez | B241: 25 | C241: Elche | D241: D(R),M(R) | E241: es | F241: 6.7768421 | G241: 0 | H241: 0.10895884 | I241: 0.008722155 | J241: 0.21791768 | K241: 1.0895884 | L241: 53.989104 | M241: 1.1440678 | N241: 0.8716707 | O241: 1.3075061 | P241: 0.32687651 | Q241: 0.76271186 | R241: 0.49031477 | S241: 91.321897 | T241: 0.32687651 | U241: 0.98062954 | V241: 0 | W241: 65.67 | X241: 5.15 | Y241: 64.81 | Z241: 36.91 | AA241: 54.94 | AB241: 95.71 | AC241: 63.95 | AD241: 18.03
A242: Álvaro Odriozola | B242: 30 | C242: Fiorentina | D242: D(R) | E242: es | F242: 6.3404 | G242: 0.052023121 | H242: 0.052023121 | I242: null | J242: 0.20809249 | K242: null | L242: null | M242: null | N242: null | O242: null | P242: null | Q242: null | R242: 0.052023121 | S242: 88.902148 | T242: null | U242: null | V242: 37.28 | W242: 35.5 | X242: 0 | Y242: 0 | Z242: 0 | AA242: 0 | AB242: 87.57 | AC242: 0 | AD242: 1.18
A243: Álvaro Rodríguez | B243: 21 | C243: Elche | D243: FW | E243: null | F243: 6.9177273 | G243: 0.3166784 | H243: 0.25334272 | I243: 0.48622801 | J243: 3.0401126 | K243: 1.6467277 | L243: 22.800844 | M243: 0.19000704 | N243: 0.12667136 | O243: 0.82336383 | P243: 0.063335679 | Q243: 1.773399 | R243: 5.13019 | S243: 65.833333 | T243: 1.9634061 | U243: 4.1168191 | V243: 84.55 | W243: 91.42 | X243: 93.99 | Y243: 85.84 | Z243: 14.16 | AA243: 6.44 | AB243: 3 | AC243: 93.13 | AD243: 99.57
A244: Alysson Edward | B244: 19 | C244: Gremio | D244: AM(R) | E244: br | F244: 6.63 | G244: 0.051993068 | H244: 0.10398614 | I244: 0.20121837 | J244: 2.0797227 | K244: 0.51993068 | L244: 23.240901 | M244: 0.20797227 | N244: 0.83188908 | O244: 2.4436742 | P244: 0.051993068 | Q244: 1.7677643 | R244: 2.2357019 | S244: 77.852349 | T244: 2.287695 | U244: 3.5355286 | V244: 40.51 | W244: 68.49 | X244: 74.6 | Y244: 28.94 | Z244: 87.46 | AA244: 54.98 | AB244: 17.36 | AC244: 92.93 | AD244: 85.53
A245: Amad Diallo | B245: 23 | C245: Man Utd | D245: M(CR) | E245: ci | F245: 7.0713381 | G245: 0.31153612 | H245: 0.16011912 | I245: 0.14479224 | J245: 2.1729209 | K245: 1.8387593 | L245: 41.01138 | M245: 0.51603608 | N245: 0.73010839 | O245: 1.4793615 | P245: 0.071357435 | Q245: 1.9362231 | R245: 0.47513609 | S245: 86.745933 | T245: 1.4750104 | U245: 2.3565358 | V245: 79.5 | W245: 74.64 | X245: 51.69 | Y245: 90.01 | Z245: 43.66 | AA245: 42.83 | AB245: 79.47 | AC245: 95.58 | AD245: 14.86
A246: Amadou Dante | B246: 25 | C246: Arouca | D246: D(L) | E246: ml | F246: 6.35875 | G246: 0 | H246: 0 | I246: 0.0091443396 | J246: 0.50943396 | K246: 0.8490566 | L246: 37.358491 | M246: 0.59433962 | N246: 1.4433962 | O246: 2.5471698 | P246: 0.16981132 | Q246: 0.67924528 | R246: 0.33962264 | S246: 78.636364 | T246: 0.50943396 | U246: 1.1886792 | V246: 0 | W246: 0 | X246: 2.75 | Y246: 52.2 | Z246: 87.36 | AA246: 89.01 | AB246: 36.81 | AC246: 56.04 | AD246: 9.89
A247: Amadou Haidara | B247: 28 | C247: RBL | D247: M(CLR) | E247: ml | F247: 6.7177595 | G247: 0.097998762 | H247: 0.063957087 | I247: 0.09558562 | J247: 1.1728904 | K247: 0.66536002 | L247: 53.062719 | M247: 0.070146482 | N247: 1.2966784 | O247: 2.0569424 | P247: 0.50753043 | Q247: 0.6478234 | R247: 1.8269032 | S247: 83.22018 | T247: 0.66020219 | U247: 0.67464411 | V247: 39.92 | W247: 42.37 | X247: 43.45 | Y247: 36.02 | Z247: 76.17 | AA247: 75.15 | AB247: 66.19 | AC247: 48.87 | AD247: 65.67
A248: Amadou Mbengue | B248: 24 | C248: QPR | D248: D(CR) | E248: sn | F248: 6.57248 | G248: 0.06804616 | H248: 0 | I248: 0.0084353363 | J248: 0.43573418 | K248: 0.35694389 | L248: 34.647433 | M248: 0.29964186 | N248: 1.2391564 | O248: 2.0903303 | P248: 0.75447672 | Q248: 0.39156387 | R248: 1.6402706 | S248: 76.985931 | T248: 0.67688022 | U248: 1.3239156 | V248: 46.07 | W248: 0 | X248: 6.07 | Y248: 18.73 | Z248: 78.49 | AA248: 69.22 | AB248: 43.02 | AC248: 36.89 | AD248: 51.38
A249: Amadou Onana | B249: 24 | C249: Aston Villa | D249: DMC | E249: be | F249: 6.7087407 | G249: 0.1009674 | H249: 0.016096252 | I249: 0.12018552 | J249: 1.0455248 | K249: 0.61751077 | L249: 41.352004 | M249: 0.035119096 | N249: 1.3045281 | O249: 2.78392 | P249: 0.40460125 | Q249: 0.60580441 | R249: 2.1825055 | S249: 85.566625 | T249: 0.52093326 | U249: 1.1047882 | V249: 52.34 | W249: 11.56 | X249: 55.31 | Y249: 35.39 | Z249: 88.58 | AA249: 79.8 | AB249: 67.75 | AC249: 45.16 | AD249: 81.13
A250: Amar Dedic | B250: 23 | C250: Benfica | D250: D(LR),M(R) | E250: ba | F250: 7.0213333 | G250: 0.069284065 | H250: 0.20785219 | I250: 0.037787529 | J250: 0.69284065 | K250: 1.2471132 | L250: 45.866051 | M250: 0.41570439 | N250: 0.90069284 | O250: 1.7321016 | P250: 0.13856813 | Q250: 1.7321016 | R250: 0.48498845 | S250: 84.89426 | T250: 0.83140878 | U250: 1.3163972 | V250: 46.89 | W250: 87.01 | X250: 31.64 | Y250: 79.1 | Z250: 62.71 | AA250: 59.32 | AB250: 66.1 | AC250: 93.22 | AD250: 15.25
A251: Amar Fatah | B251: 22 | C251: Dundee United | D251: AM(LR) | E251: se | F251: 6.70875 | G251: 0.30695771 | H251: 0.18417462 | I251: 0.25513097 | J251: 2.148704 | K251: 1.1050477 | L251: 17.619372 | M251: 0.92087312 | N251: 1.0436562 | O251: 1.7189632 | P251: 0.061391542 | Q251: 1.9645293 | R251: 1.7189632 | S251: 66.202091 | T251: 1.7803547 | U251: 4.9113233 | V251: 87.41 | W251: 84.62 | X251: 78.32 | Y251: 65.03 | Z251: 66.43 | AA251: 69.23 | AB251: 7.69 | AC251: 96.5 | AD251: 58.74
A252: Amari'i Bell | B252: 31 | C252: Charlton | D252: D(CL),M(L) | E252: jm | F252: 6.6589366 | G252: 0.0094757841 | H252: 0.013465588 | I252: 0.0070992076 | J252: 0.23190735 | K252: 0.48525989 | L252: 34.777624 | M252: 0.22741882 | N252: 1.1156489 | O252: 1.6662418 | P252: 0.48176881 | Q252: 0.56355979 | R252: 1.5315859 | S252: 74.536644 | T252: 0.4972293 | U252: 1.1161476 | V252: 10.2 | W252: 11.71 | X252: 4.62 | Y252: 27.42 | Z252: 55.69 | AA252: 67.41 | AB252: 29.07 | AC252: 46.19 | AD252: 55.35
A253: Ameen Al Dakhil | B253: 24 | C253: Burnley | D253: D(C) | E253: be | F253: 6.327529 | G253: 0.031155883 | H253: 0 | I253: 0.038253193 | J253: 0.44708692 | K253: 0.23834251 | L253: 49.776197 | M253: 0.031155883 | N253: 1.3412608 | O253: 1.1745768 | P253: 0.49849413 | Q253: 0.16356839 | R253: 1.2882958 | S253: 83.428312 | T253: 0.25703604 | U253: 0.46889604 | V253: 16.86 | W253: 0 | X253: 33.63 | Y253: 11.61 | Z253: 22.42 | AA253: 68.9 | AB253: 73.8 | AC253: 11 | AD253: 57.48
A254: Amin Cherni | B254: 24 | C254: Goztepe | D254: M(L) | E254: tn | F254: 6.7873913 | G254: 0 | H254: 0.17612524 | I254: 0.01662182 | J254: 0.57240705 | K254: 1.4530333 | L254: 22.059687 | M254: 1.9373777 | N254: 0.3962818 | O254: 1.8052838 | P254: 0.044031311 | Q254: 0.26418787 | R254: 1.2328767 | S254: 68.463074 | T254: 0.7925636 | U254: 1.5410959 | V254: 0 | W254: 84.57 | X254: 10.64 | Y254: 80.85 | Z254: 74.47 | AA254: 21.81 | AB254: 5.85 | AC254: 23.4 | AD254: 57.98
... A296: Andreas Skov Olsen | B296: 26 | C296: Club Brugge | D296: M(CR) | E296: dk | F296: 7.1729889 | G296: 0.48880767 | H296: 0.24897213 | I296: 0.26540212 | J296: 3.1235724 | K296: 2.3880767 | L296: 37.301279 | M296: 1.1843307 | N296: 0.61329374 | O296: 1.01873 | P296: 0.093650069 | Q296: 1.4287346 | R296: 0.24897213 | S296: 80.748409 | T296: 1.0872545 | U296: 1.9175423 | V296: 93.11 | W296: 88.15 | X296: 70.55 | Y296: 94.02 | Z296: 18.31 | AA296: 30.02 | AB296: 58.61 | AC296: 80.57 | AD296: 7.53
A297: Andreas Verstraeten | B297: 20 | C297: Royal Antwerp | D297: D(C),DMC | E297: be | F297: 6.375625 | G297: 0 | H297: 0.097508126 | I297: null | J297: 0 | K297: 0.78006501 | L297: 53.629469 | M297: 0.3900325 | N297: 1.3651138 | O297: 2.0476706 | P297: 0.3900325 | Q297: 0.3900325 | R297: 0.58504875 | S297: 83.090909 | T297: 0.48754063 | U297: 1.2676056 | V297: 0 | W297: 64.25 | X297: 99.48 | Y297: 47.15 | Z297: 75.13 | AA297: 82.38 | AB297: 69.95 | AC297: 39.38 | AD297: 21.24
A298: Andreas Weimann | B298: 34 | C298: Blackburn | D298: M(CLR),FW | E298: at | F298: 6.6879251 | G298: 0.36246211 | H298: 0.17464083 | I298: 0.091519705 | J298: 1.6488731 | K298: 0.94503756 | L298: 22.738236 | M298: 0.26624489 | N298: 0.53512587 | O298: 0.65045473 | P298: 0.12455516 | Q298: 0.52194543 | R298: 0.7993937 | S298: 72.901724 | T298: 0.59180177 | U298: 1.3496771 | V298: 88.08 | W298: 84.63 | X298: 36.22 | Y298: 60.02 | Z298: 9.73 | AA298: 26.66 | AB298: 28.22 | AC298: 39.58 | AD298: 24.15
A299: Andrei Ratiu | B299: 27 | C299: Rayo Vallecano | D299: D(R),M(R) | E299: ro | F299: 6.9463401 | G299: 0.034421085 | H299: 0.11237472 | I299: 0.080387811 | J299: 0.95872844 | K299: 1.1024871 | L299: 41.724429 | M299: 0.45253602 | N299: 1.0518679 | O299: 2.0925995 | P299: 0.12654811 | Q299: 2.057166 | R299: 0.6276786 | S299: 83.658731 | T299: 1.4102521 | U299: 2.0784261 | V299: 24.78 | W299: 64.6 | X299: 44.67 | Y299: 65.19 | Z299: 74.45 | AA299: 68.77 | AB299: 55.87 | AC299: 94.97 | AD299: 28.38
A300: Andrej Ilic | B300: 25 | C300: Union Berlin | D300: FW | E300: rs | F300: 6.65661 | G300: 0.27206298 | H300: 0.27402027 | I300: 0.50725575 | J300: 2.7323735 | K300: 1.0608499 | L300: 16.942282 | M300: 0.078291505 | N300: 0.16636945 | O300: 0.14483928 | P300: 0.33469619 | Q300: 0.26814841 | R300: 5.7172372 | S300: 58.573986 | T300: 1.3564003 | U300: 3.1003436 | V300: 57.53 | W300: 63.42 | X300: 93.76 | Y300: 56.63 | Z300: 0.48 | AA300: 10.29 | AB300: 0 | AC300: 26.36 | AD300: 99.36
A301: Andrej Kramaric | B301: 34 | C301: Hoffenheim | D301: AM(CLR),FW | E301: hr | F301: 6.8730979 | G301: 0.45137679 | H301: 0.23527361 | I301: 0.3988503 | J301: 2.6002091 | K301: 1.8264204 | L301: 37.435227 | M301: 0.95387475 | N301: 0.31195539 | O301: 0.35320088 | P301: 0.081910073 | Q301: 0.85860346 | R301: 0.32473568 | S301: 83.524409 | T301: 1.1752062 | U301: 1.7561287 | V301: 88.43 | W301: 83.64 | X301: 80.53 | Y301: 82.72 | Z301: 3.31 | AA301: 14.65 | AB301: 64.46 | AC301: 63.8 | AD301: 7.19
A302: Andrés Gómez | B302: 23 | C302: Vasco da Gama | D302: AM(LR) | E302: co | F302: 6.78125 | G302: 0.087124879 | H302: 0.43562439 | I302: 0.27392933 | J302: 2.7008712 | K302: 1.8296225 | L302: 18.470474 | M302: 0.60987415 | N302: 0.60987415 | O302: 0.95837367 | P302: 0.087124879 | Q302: 2.2652469 | R302: 0.43562439 | S302: 77.358491 | T302: 2.0909971 | U302: 3.7463698 | V302: 54.98 | W302: 99.36 | X302: 85.53 | Y302: 90.68 | Z302: 21.22 | AA302: 36.66 | AB302: 14.79 | AC302: 97.43 | AD302: 14.79
A303: Andrés Hurtado | B303: 24 | C303: Red Bull Bragantino | D303: D(R) | E303: ec | F303: 6.6167041 | G303: 0.021792031 | H303: 0.037046453 | I303: 0.0178103 | J303: 0.49141031 | K303: 0.71586823 | L303: 36.855773 | M303: 0.75945229 | N303: 1.104856 | O303: 1.8032906 | P303: 0.2745796 | Q303: 0.94468456 | R303: 1.1800385 | S303: 80.584056 | T303: 0.50121672 | U303: 1.1277376 | V303: 17.31 | W303: 19.67 | X303: 6.89 | Y303: 37.84 | Z303: 60.95 | AA303: 69.93 | AB303: 33.18 | AC303: 66.7 | AD303: 52.24
A304: Andrew Hughes | B304: 33 | C304: Preston | D304: D(CL),M(L) | E304: gb-wls | F304: 6.7452954 | G304: 0.019919016 | H304: 0.030331229 | I304: 0.029818858 | J304: 0.49344835 | K304: 0.40833983 | L304: 46.252408 | M304: 0.20190639 | N304: 1.1457961 | O304: 1.8456779 | P304: 0.49163753 | Q304: 0.1570886 | R304: 3.697241 | S304: 73.679083 | T304: 0.29787983 | U304: 0.81260532 | V304: 16.31 | W304: 23.03 | X304: 16.16 | Y304: 22.36 | Z304: 67.97 | AA304: 70.17 | AB304: 25.34 | AC304: 12.04 | AD304: 89.71
A305: Andrew Moran | B305: 22 | C305: Stoke | D305: M(CLR) | E305: ie | F305: 6.5216136 | G305: 0.13024933 | H305: 0.18509115 | I305: 0.15076737 | J305: 1.1642462 | K305: 1.4658762 | L305: 36.56807 | M305: 0.23993297 | N305: 0.64439141 | O305: 2.4050424 | P305: 0.22507998 | Q305: 0.92202813 | R305: 0.37818006 | S305: 77.586442 | T305: 1.5835576 | U305: 1.8531966 | V305: 62.36 | W305: 79.9 | X305: 61.42 | Y305: 79.95 | Z305: 84.06 | AA305: 36.59 | AB305: 35.21 | AC305: 66.07 | AD305: 10.19
...

Sheet RADAR_DATA
A1: Metric | B1: Player 1 | C1: Player 2
A2: Goals | B2: =IFERROR(XLOOKUP(DASHBOARD!$B$6,DATA!$A:$A,DATA!$V:$V,0),0) | C2: =IFERROR(XLOOKUP(DASHBOARD!$I$6,DATA!$A:$A,DATA!$V:$V,0),0)
A3: xG | B3: =IFERROR(XLOOKUP(DASHBOARD!$B$6,DATA!$A:$A,DATA!$X:$X,0),0) | C3: =IFERROR(XLOOKUP(DASHBOARD!$I$6,DATA!$A:$A,DATA!$X:$X,0),0)
A4: Key Passes | B4: =IFERROR(XLOOKUP(DASHBOARD!$B$6,DATA!$A:$A,DATA!$Y:$Y,0),0) | C4: =IFERROR(XLOOKUP(DASHBOARD!$I$6,DATA!$A:$A,DATA!$Y:$Y,0),0)
A5: Tackles | B5: =IFERROR(XLOOKUP(DASHBOARD!$B$6,DATA!$A:$A,DATA!$Z:$Z,0),0) | C5: =IFERROR(XLOOKUP(DASHBOARD!$I$6,DATA!$A:$A,DATA!$Z:$Z,0),0)
A6: Pass % | B6: =IFERROR(XLOOKUP(DASHBOARD!$B$6,DATA!$A:$A,DATA!$AB:$AB,0),0) | C6: =IFERROR(XLOOKUP(DASHBOARD!$I$6,DATA!$A:$A,DATA!$AB:$AB,0),0)
A7: Dribbles | B7: =IFERROR(XLOOKUP(DASHBOARD!$B$6,DATA!$A:$A,DATA!$AC:$AC,0),0) | C7: =IFERROR(XLOOKUP(DASHBOARD!$I$6,DATA!$A:$A,DATA!$AC:$AC,0),0)

Sheet BAR_DATA
A1: Metric | B1: Player 1 | C1: Player 2
A2: Goals/90 | B2: =IFERROR(XLOOKUP(DASHBOARD!$B$6,DATA!$A:$A,DATA!$G:$G,0),0) | C2: =IFERROR(XLOOKUP(DASHBOARD!$I$6,DATA!$A:$A,DATA!$G:$G,0),0)
A3: Assists/90 | B3: =IFERROR(XLOOKUP(DASHBOARD!$B$6,DATA!$A:$A,DATA!$H:$H,0),0) | C3: =IFERROR(XLOOKUP(DASHBOARD!$I$6,DATA!$A:$A,DATA!$H:$H,0),0)
A4: xG/90 | B4: =IFERROR(XLOOKUP(DASHBOARD!$B$6,DATA!$A:$A,DATA!$I:$I,0),0) | C4: =IFERROR(XLOOKUP(DASHBOARD!$I$6,DATA!$A:$A,DATA!$I:$I,0),0)
A5: Shots/90 | B5: =IFERROR(XLOOKUP(DASHBOARD!$B$6,DATA!$A:$A,DATA!$J:$J,0),0) | C5: =IFERROR(XLOOKUP(DASHBOARD!$I$6,DATA!$A:$A,DATA!$J:$J,0),0)
A6: Key Pass/90 | B6: =IFERROR(XLOOKUP(DASHBOARD!$B$6,DATA!$A:$A,DATA!$K:$K,0),0) | C6: =IFERROR(XLOOKUP(DASHBOARD!$I$6,DATA!$A:$A,DATA!$K:$K,0),0)
A7: Passes/90 | B7: =IFERROR(XLOOKUP(DASHBOARD!$B$6,DATA!$A:$A,DATA!$L:$L,0),0) | C7: =IFERROR(XLOOKUP(DASHBOARD!$I$6,DATA!$A:$A,DATA!$L:$L,0),0)
A8: Crosses/90 | B8: =IFERROR(XLOOKUP(DASHBOARD!$B$6,DATA!$A:$A,DATA!$M:$M,0),0) | C8: =IFERROR(XLOOKUP(DASHBOARD!$I$6,DATA!$A:$A,DATA!$M:$M,0),0)
A9: Interc./90 | B9: =IFERROR(XLOOKUP(DASHBOARD!$B$6,DATA!$A:$A,DATA!$N:$N,0),0) | C9: =IFERROR(XLOOKUP(DASHBOARD!$I$6,DATA!$A:$A,DATA!$N:$N,0),0)
A10: Tackles/90 | B10: =IFERROR(XLOOKUP(DASHBOARD!$B$6,DATA!$A:$A,DATA!$O:$O,0),0) | C10: =IFERROR(XLOOKUP(DASHBOARD!$I$6,DATA!$A:$A,DATA!$O:$O,0),0)
A11: Blocks/90 | B11: =IFERROR(XLOOKUP(DASHBOARD!$B$6,DATA!$A:$A,DATA!$P:$P,0),0) | C11: =IFERROR(XLOOKUP(DASHBOARD!$I$6,DATA!$A:$A,DATA!$P:$P,0),0)
A12: Dribbles/90 | B12: =IFERROR(XLOOKUP(DASHBOARD!$B$6,DATA!$A:$A,DATA!$Q:$Q,0),0) | C12: =IFERROR(XLOOKUP(DASHBOARD!$I$6,DATA!$A:$A,DATA!$Q:$Q,0),0)
A13: Aerials/90 | B13: =IFERROR(XLOOKUP(DASHBOARD!$B$6,DATA!$A:$A,DATA!$R:$R,0),0) | C13: =IFERROR(XLOOKUP(DASHBOARD!$I$6,DATA!$A:$A,DATA!$R:$R,0),0)
